breathe_design/__init__.py
breathe_design/api_interface.py
breathe_design/api_utils.py
breathe_design/cycler.py
breathe_design/cycling_protocols.json
breathe_design/device_flow_auth.py
breathe_design/dynamic_analysis.py
breathe_design/format.py
breathe_design/montecarlo_utils.py
breathe_design/parameter_bounds.json
breathe_design/parameter_validator.py
breathe_design/plots.py
breathe_design/results.py
breathe_design/utilities.py
breathe_design-1.2.1.dist-info/METADATA
breathe_design-1.2.1.dist-info/WHEEL
breathe_design-1.2.1.dist-info/RECORD
