Metadata-Version: 2.4
Name: breathe_design
Version: 1.2.1
Summary: A Python library for interating with the Breathe Design api and analyzing and visualizing Breathe Design data
Requires-Python: >=3.9
Requires-Dist: ipykernel
Requires-Dist: nbformat>=4.2.0
Requires-Dist: numpy
Requires-Dist: pandas
Requires-Dist: plotly
Requires-Dist: pydantic
Requires-Dist: pydantic-settings
Requires-Dist: requests
Requires-Dist: scipy
Requires-Dist: tqdm
Provides-Extra: dev
Requires-Dist: httpx; extra == 'dev'
Requires-Dist: nbclient; extra == 'dev'
Requires-Dist: pytest; extra == 'dev'
Requires-Dist: ruff; extra == 'dev'
Provides-Extra: docs
Requires-Dist: mkdocs; extra == 'docs'
Requires-Dist: mkdocs-jupyter; extra == 'docs'
Requires-Dist: mkdocs-macros-plugin; extra == 'docs'
Requires-Dist: mkdocs-material; extra == 'docs'
Requires-Dist: mkdocstrings[python]; extra == 'docs'
